zensols/rbak/__init__.py
zensols/rbak/backup.py
zensols/rbak/cli.py
zensols/rbak/domain.py
zensols.rbak-0.4.dist-info/METADATA
zensols.rbak-0.4.dist-info/RECORD
zensols.rbak-0.4.dist-info/WHEEL
zensols.rbak-0.4.dist-info/entry_points.txt
zensols.rbak-0.4.dist-info/top_level.txt
