Metadata-Version: 2.1
Name: zensols.rbak
Version: 0.4
Summary: Simple program to mount file systems and backup directories
Home-page: https://github.com/plandes/rbak
Author: Paul Landes
Author-email: landes@mailc.net
License: UNKNOWN
Download-URL: https://github.com/plandes/rbak/releases/download/v0.0.4/zensols.rbak-0.4-py3-none-any.whl
Keywords: tooling
Platform: UNKNOWN
